README.txt
pytest_cache.py
setup.cfg
setup.py
pytest_cache.egg-info/PKG-INFO
pytest_cache.egg-info/SOURCES.txt
pytest_cache.egg-info/dependency_links.txt
pytest_cache.egg-info/entry_points.txt
pytest_cache.egg-info/requires.txt
pytest_cache.egg-info/top_level.txt