Metadata-Version: 1.1
Name: pytest-cache
Version: 0.9
Summary: pytest plugin with mechanisms for caching across test runs
Home-page: http://bitbucket.org/hpk42/pytest-cache/
Author: Holger Krekel
Author-email: holger.krekel@gmail.com
License: UNKNOWN
Platform: UNKNOWN
Classifier: Development Status :: 3 - Alpha
Classifier: Intended Audience :: Developers
Classifier: License :: OSI Approved :: GNU General Public License (GPL)
Classifier: Operating System :: POSIX
Classifier: Operating System :: Microsoft :: Windows
Classifier: Operating System :: MacOS :: MacOS X
Classifier: Topic :: Software Development :: Testing
Classifier: Topic :: Software Development :: Libraries
Classifier: Topic :: Utilities
Classifier: Programming Language :: Python
Classifier: Programming Language :: Python :: 3
